leneda/__init__.py
leneda/client.py
leneda/exceptions.py
leneda/models.py
leneda/obis_codes.py
leneda/py.typed
leneda/version.py
leneda_client-0.6.0.dist-info/licenses/LICENSE
leneda_client-0.6.0.dist-info/METADATA
leneda_client-0.6.0.dist-info/WHEEL
leneda_client-0.6.0.dist-info/top_level.txt
leneda_client-0.6.0.dist-info/RECORD
