Metadata-Version: 2.4
Name: leneda-client
Version: 0.6.0
Summary: Python client for the Leneda energy data platform
Home-page: https://github.com/fedus/leneda-client
Author: fedus
Author-email: fedus@dillendapp.eu
Project-URL: Bug Reports, https://github.com/yourusername/leneda-client/issues
Project-URL: Source, https://github.com/yourusername/leneda-client
Project-URL: Documentation, https://github.com/yourusername/leneda-client#readme
Keywords: leneda,energy,api,client
Classifier: Development Status :: 4 - Beta
Classifier: Intended Audience :: Developers
Classifier: License :: OSI Approved :: MIT License
Classifier: Programming Language :: Python :: 3
Classifier: Programming Language :: Python :: 3.8
Classifier: Programming Language :: Python :: 3.9
Classifier: Programming Language :: Python :: 3.10
Classifier: Programming Language :: Python :: 3.11
Classifier: Topic :: Software Development :: Libraries :: Python Modules
Classifier: Topic :: Utilities
Requires-Python: >=3.8
License-File: LICENSE
Requires-Dist: aiohttp>=3.9.0
Requires-Dist: python-dateutil>=2.8.2
Requires-Dist: pytest-asyncio>=0.23.0
Dynamic: author
Dynamic: author-email
Dynamic: classifier
Dynamic: description
Dynamic: description-content-type
Dynamic: home-page
Dynamic: keywords
Dynamic: license-file
Dynamic: project-url
Dynamic: requires-dist
Dynamic: requires-python
Dynamic: summary
